ufaas_fastapi_business/__init__.py
ufaas_fastapi_business/middlewares.py
ufaas_fastapi_business/models.py
ufaas_fastapi_business/routes.py
ufaas_fastapi_business/schemas.py
ufaas_fastapi_business/core/__init__.py
ufaas_fastapi_business/core/app_auth.py
ufaas_fastapi_business/core/config.py
ufaas_fastapi_business/core/enums.py
ufaas_fastapi_business/core/exceptions.py
ufaas_fastapi_business/core/middlewares.py
ufaas_fastapi_business-0.5.2.dist-info/LICENSE.txt
ufaas_fastapi_business-0.5.2.dist-info/METADATA
ufaas_fastapi_business-0.5.2.dist-info/WHEEL
ufaas_fastapi_business-0.5.2.dist-info/top_level.txt
ufaas_fastapi_business-0.5.2.dist-info/RECORD
