Metadata-Version: 2.2
Name: ufaas-fastapi-business
Version: 0.5.2
Summary: A simple boilerplate application, including models and schemas and abstract router, for FastAPI with MongoDB for Ufaas extensions with business logic
Author-email: Mahdi Kiani <mahdikiany@gmail.com>
Maintainer-email: Mahdi Kiani <mahdikiany@gmail.com>
License: Copyright (c) 2016 The Python Packaging Authority (PyPA)
Project-URL: Homepage, https://github.com/ufaasio/ufaas-fastapi-mongo-base-app
Project-URL: Bug Reports, https://github.com/ufaasio/ufaas-fastapi-mongo-base-app/issues
Project-URL: Funding, https://github.com/ufaasio/ufaas-fastapi-mongo-base-app
Project-URL: Say Thanks!, https://saythanks.io/to/mahdikiani
Project-URL: Source, https://github.com/ufaasio/ufaas-fastapi-mongo-base-app
Keywords: fastapi,ufaas
Classifier: Development Status :: 3 - Alpha
Classifier: Intended Audience :: Developers
Classifier: Topic :: Software Development :: Build Tools
Classifier: License :: OSI Approved :: MIT License
Classifier: Programming Language :: Python :: 3
Classifier: Programming Language :: Python :: 3.10
Classifier: Programming Language :: Python :: 3.11
Classifier: Programming Language :: Python :: 3.12
Classifier: Programming Language :: Python :: 3 :: Only
Requires-Python: >=3.9
License-File: LICENSE.txt
Requires-Dist: pydantic>=1.8.2
Requires-Dist: requests>=2.26.0
Requires-Dist: pyjwt[crypto]
Requires-Dist: singleton_package
Requires-Dist: fastapi-mongo-base
Requires-Dist: usso[fastapi]
